bywords/__init__.py
bywords/__main__.py
bywords/adjust.py
bywords/bywords.py
sangfroid/__init__.py
sangfroid/animation.py
sangfroid/field.py
sangfroid/format.py
sangfroid/keyframe.py
sangfroid/registry.py
sangfroid/t.py
sangfroid/util.py
sangfroid/layer/__init__.py
sangfroid/layer/blurs.py
sangfroid/layer/geometry.py
sangfroid/layer/group.py
sangfroid/layer/layer.py
sangfroid/layer/other.py
sangfroid/layer/stylise.py
sangfroid/layer/tbd.py
sangfroid/layer/text.py
sangfroid/layer/time.py
sangfroid/layer/transform.py
sangfroid/value/__init__.py
sangfroid/value/blendmethod.py
sangfroid/value/canvas.py
sangfroid/value/color.py
sangfroid/value/gradient.py
sangfroid/value/simple.py
sangfroid/value/string.py
sangfroid/value/tbd.py
sangfroid/value/transformation.py
sangfroid/value/value.py
sangfroid/value/vector.py
sangfroid-0.3.0.dist-info/licenses/LICENSE
sangfroid-0.3.0.dist-info/METADATA
sangfroid-0.3.0.dist-info/WHEEL
sangfroid-0.3.0.dist-info/entry_points.txt
sangfroid-0.3.0.dist-info/top_level.txt
sangfroid-0.3.0.dist-info/RECORD
