Metadata-Version: 2.4
Name: sangfroid
Version: 0.3.0
Summary: Parses Synfig files
Author-email: Marnanel Thurman <marnanel@thurman.org.uk>
Project-URL: Homepage, https://gitlab.com/marnanel/sangfroid
Project-URL: Repository, https://gitlab.com/marnanel/sangfroid.git
Project-URL: Issues, https://gitlab.com/marnanel/sangfroid/issues
Keywords: synfig,synfigstudio,animation
Classifier: Development Status :: 2 - Pre-Alpha
Classifier: Programming Language :: Python :: 3
Classifier: License :: OSI Approved :: MIT License
Classifier: Intended Audience :: Developers
Classifier: Operating System :: OS Independent
Classifier: Topic :: Text Processing
Classifier: Topic :: Multimedia :: Graphics :: Editors :: Vector-Based
Requires-Python: >=3.8
License-File: LICENSE
Requires-Dist: beautifulsoup4==4.12.2
Requires-Dist: bs4==0.0.1
Requires-Dist: lxml==4.9.3
Requires-Dist: pysrt==1.1.2
Requires-Dist: pluggy==1.3.0
Requires-Dist: pytest==7.4.3
Requires-Dist: soupsieve==2.5
Dynamic: license-file
